phabricator/__init__.py
phabricator/_compat.py
phabricator/interfaces.json
phabricator/tests/__init__.py
phabricator/tests/test_phabricator.py
phabricator/tests/resources/__init__.py
phabricator-0.9.1.dist-info/LICENSE
phabricator-0.9.1.dist-info/METADATA
phabricator-0.9.1.dist-info/WHEEL
phabricator-0.9.1.dist-info/top_level.txt
phabricator-0.9.1.dist-info/RECORD
